SimpleNet/NeuralNetwork.py
SimpleNet/__init__.py
SimpleNet_kir486680-0.0.1.dist-info/DESCRIPTION.rst
SimpleNet_kir486680-0.0.1.dist-info/METADATA
SimpleNet_kir486680-0.0.1.dist-info/RECORD
SimpleNet_kir486680-0.0.1.dist-info/WHEEL
SimpleNet_kir486680-0.0.1.dist-info/metadata.json
SimpleNet_kir486680-0.0.1.dist-info/top_level.txt
