Metadata-Version: 2.0
Name: SimpleNet-kir486680
Version: 0.0.1
Summary: Package that helps to create neural nets
Home-page: https://github.com/kir486680
Author: Kyrylo
Author-email: kir486680@gmail.com
License: UNKNOWN
Platform: UNKNOWN
Classifier: Programming Language :: Python :: 3
Classifier: License :: OSI Approved :: MIT License
Classifier: Operating System :: OS Independent
